Metadata-Version: 2.1
Name: crawl-request
Version: 1.0.1
Summary: fast request util.
Home-page: https://cn.bing.com/
Author: znz
Author-email: zhang_naizhao@163.com
License: UNKNOWN
Platform: any
Classifier: Programming Language :: Python :: 3
Classifier: License :: OSI Approved :: MIT License
